a/__init__.py
a/b/__init__.py
a/b/pq.py
abcd_divami_testing-0.1.1.dist-info/METADATA
abcd_divami_testing-0.1.1.dist-info/WHEEL
abcd_divami_testing-0.1.1.dist-info/top_level.txt
abcd_divami_testing-0.1.1.dist-info/RECORD
