Metadata-Version: 2.4
Name: abcd-divami-testing
Version: 0.1.1
Summary: Add your description here
Requires-Python: >=3.10
Requires-Dist: build>=1.3.0
Requires-Dist: kafka>=1.3.5
Requires-Dist: numpy>=2.3.2
Requires-Dist: pandas>=2.3.2
Requires-Dist: pytest>=8.4.2
Requires-Dist: spark>=0.2.1
Requires-Dist: twine>=6.2.0
